markov_solver/__init__.py
markov_solver/cli.py
markov_solver/config/__init__.py
markov_solver/config/metadata.py
markov_solver/core/__init__.py
markov_solver/core/model/__init__.py
markov_solver/core/model/markov_chain.py
markov_solver/core/model/markov_link.py
markov_solver/core/model/markov_state.py
markov_solver/core/parser/__init__.py
markov_solver/core/parser/markov_chain_parser.py
markov_solver/utils/__init__.py
markov_solver/utils/csv_utils.py
markov_solver/utils/file_utils.py
markov_solver/utils/guiutils.py
markov_solver/utils/logutils.py
markov_solver/utils/report.py
markov_solver-1.0.1.dist-info/LICENSE
markov_solver-1.0.1.dist-info/METADATA
markov_solver-1.0.1.dist-info/WHEEL
markov_solver-1.0.1.dist-info/entry_points.txt
markov_solver-1.0.1.dist-info/top_level.txt
markov_solver-1.0.1.dist-info/RECORD
