Metadata-Version: 2.1
Name: markov-solver
Version: 1.0.1
Summary: Utility to solve Markov chains.
Home-page: https://github.com/gmarciani/markov-solver
Author: Giacomo Marciani
License: MIT License
Project-URL: Changelog, https://github.com/gmarciani/markov-solver/blob/mainline/CHANGELOG.md
Project-URL: Issue Tracker, https://github.com/gmarciani/markov-solver/issues
Project-URL: Documentation, https://github.com/gmarciani/markov-solver
Classifier: Development Status :: 1 - Planning
Classifier: Environment :: Console
Classifier: Programming Language :: Python
Classifier: Programming Language :: Python :: 3
Classifier: Programming Language :: Python :: 3.6
Classifier: Programming Language :: Python :: 3.7
Classifier: Programming Language :: Python :: 3.8
Classifier: Programming Language :: Python :: 3.9
Classifier: Programming Language :: Python :: 3.10
Classifier: Programming Language :: Python :: 3.11
Classifier: Topic :: Scientific/Engineering
Classifier: License :: OSI Approved :: MIT License
Requires-Python: >=3.6
License-File: LICENSE
Requires-Dist: setuptools ~=72.1.0
Requires-Dist: click ~=8.1.7
Requires-Dist: colored ~=2.2.4
Requires-Dist: graphviz ~=0.20.3
Requires-Dist: networkx ~=3.2.1
Requires-Dist: numpy ~=2.0.1
Requires-Dist: pyfiglet ~=1.0.2
Requires-Dist: pyyaml ~=6.0.2
Requires-Dist: scipy ~=1.13.1
Requires-Dist: sympy ~=1.13.1
